[
  {
    "lat": -6.2628908,
    "lon": 106.8822289,
    "failed": false,
    "year": "2023",
    "tablet": "Agapao",
    "city": "Jakarta Timur",
    "state": "DKI Jakarta",
    "country": "INDONESIA",
    "color": "#41ab5d",
    "count": 1
  },
  {
    "lat": -7.6290837,
    "lon": 111.5168819,
    "failed": false,
    "year": "2023",
    "tablet": "Agapao",
    "city": "Madiun",
    "state": "Jawa Timur",
    "country": "INDONESIA",
    "color": "#41ab5d",
    "count": 1
  },
  {
    "lat": -2.9888243,
    "lon": 104.7568507,
    "failed": false,
    "year": "2023",
    "tablet": "Agapao",
    "city": "Palembang",
    "state": "Sumatera Selatan",
    "country": "INDONESIA",
    "color": "#41ab5d",
    "count": 1
  },
  {
    "lat": 1.7448605,
    "lon": 100.5763381,
    "failed": false,
    "year": "2023",
    "tablet": "Agapao",
    "city": "Bagan Sinembah",
    "state": "Riau",
    "country": "INDONESIA",
    "color": "#41ab5d",
    "count": 1
  },
  {
    "lat": -6.2628908,
    "lon": 106.8822289,
    "failed": false,
    "year": "2024",
    "tablet": "Agapao",
    "city": "Jakarta Timur",
    "state": "DKI Jakarta",
    "country": "INDONESIA",
    "color": "#41ab5d",
    "count": 1
  },
  {
    "lat": 2.1239421,
    "lon": 99.9894967,
    "failed": false,
    "year": "2023",
    "tablet": "Agapao",
    "city": "Pangkatan",
    "state": "Sumatera Utara",
    "country": "INDONESIA",
    "color": "#41ab5d",
    "count": 1
  },
  {
    "lat": 3.5894617,
    "lon": 98.6741623,
    "failed": false,
    "year": "2024",
    "tablet": "Agapao",
    "city": "Medan",
    "state": "Sumatera Utara",
    "country": "INDONESIA",
    "color": "#41ab5d",
    "count": 1
  },
  {
    "lat": 2.3334951,
    "lon": 99.0667621,
    "failed": false,
    "year": "2025",
    "tablet": "Agapao",
    "city": "Balige",
    "state": "Sumatera Utara",
    "country": "INDONESIA",
    "color": "#41ab5d",
    "count": 1
  },
  {
    "lat": 2.260108,
    "lon": 98.7500083,
    "failed": false,
    "year": "2025",
    "tablet": "Agapao",
    "city": "Dolok Sanggul",
    "state": "Sumatera Utara",
    "country": "INDONESIA",
    "color": "#41ab5d",
    "count": 1
  },
  {
    "lat": 1.6631967,
    "lon": 101.4470369,
    "failed": false,
    "year": "2024",
    "tablet": "Agapao",
    "city": "Dumai",
    "state": "Riau",
    "country": "INDONESIA",
    "color": "#41ab5d",
    "count": 1
  },
  {
    "lat": -0.2827322,
    "lon": 102.2680954,
    "failed": false,
    "year": "2023",
    "tablet": "Agapao",
    "city": "Lirik",
    "state": "Riau",
    "country": "INDONESIA",
    "color": "#41ab5d",
    "count": 1
  },
  {
    "lat": -6.5962986,
    "lon": 106.7972421,
    "failed": false,
    "year": "2023",
    "tablet": "Agapao",
    "city": "Bogor",
    "state": "Jawa Barat",
    "country": "INDONESIA",
    "color": "#41ab5d",
    "count": 1
  },
  {
    "lat": -7.6290837,
    "lon": 111.5168819,
    "failed": false,
    "year": "2023",
    "tablet": "Agapao",
    "city": "Madiun",
    "state": "Jawa Timur",
    "country": "INDONESIA",
    "color": "#41ab5d",
    "count": 1
  },
  {
    "lat": -6.1761924,
    "lon": 106.6382161,
    "failed": false,
    "year": "2023",
    "tablet": "Agapao",
    "city": "Tangerang",
    "state": "Banten",
    "country": "INDONESIA",
    "color": "#41ab5d",
    "count": 1
  },
  {
    "lat": -6.2628908,
    "lon": 106.8822289,
    "failed": false,
    "year": "2023",
    "tablet": "Agapao",
    "city": "Jakarta Timur",
    "state": "DKI Jakarta",
    "country": "INDONESIA",
    "color": "#41ab5d",
    "count": 1
  },
  {
    "lat": -6.2838694,
    "lon": 106.8048297,
    "failed": false,
    "year": "2023",
    "tablet": "Agapao",
    "city": "Jakarta Selatan",
    "state": "DKI Jakarta",
    "country": "INDONESIA",
    "color": "#41ab5d",
    "count": 1
  },
  {
    "lat": -6.2628908,
    "lon": 106.8822289,
    "failed": false,
    "year": "2023",
    "tablet": "Agapao",
    "city": "Jakarta Timur",
    "state": "DKI Jakarta",
    "country": "INDONESIA",
    "color": "#41ab5d",
    "count": 1
  },
  {
    "lat": -2.4833826,
    "lon": 117.8902853,
    "failed": true,
    "year": "2024",
    "tablet": "Agapao",
    "city": "Kecamatan Parmaksian",
    "state": "North Sumatra",
    "country": "INDONESIA",
    "color": "#FF0000",
    "count": 1
  },
  {
    "lat": -6.2628908,
    "lon": 106.8822289,
    "failed": false,
    "year": "2023",
    "tablet": "Agapao",
    "city": "Jakarta Timur",
    "state": "DKI Jakarta",
    "country": "INDONESIA",
    "color": "#41ab5d",
    "count": 1
  },
  {
    "lat": -0.3731888,
    "lon": 102.2797084,
    "failed": false,
    "year": "2024",
    "tablet": "Agapao",
    "city": "Air Molek",
    "state": "Riau",
    "country": "INDONESIA",
    "color": "#41ab5d",
    "count": 1
  },
  {
    "lat": 0.7833163,
    "lon": 101.4597196,
    "failed": false,
    "year": "2023",
    "tablet": "Agapao",
    "city": "Minas",
    "state": "Riau",
    "country": "INDONESIA",
    "color": "#41ab5d",
    "count": 1
  },
  {
    "lat": 3.5894617,
    "lon": 98.6741623,
    "failed": false,
    "year": "2025",
    "tablet": "Agapao",
    "city": "Medan",
    "state": "Sumatera Utara",
    "country": "INDONESIA",
    "color": "#41ab5d",
    "count": 1
  },
  {
    "lat": -6.2628908,
    "lon": 106.8822289,
    "failed": false,
    "year": "2025",
    "tablet": "Agapao",
    "city": "Jakarta Timur",
    "state": "DKI Jakarta",
    "country": "INDONESIA",
    "color": "#41ab5d",
    "count": 1
  },
  {
    "lat": 3.5894617,
    "lon": 98.6741623,
    "failed": false,
    "year": "2023",
    "tablet": "Agapao",
    "city": "Medan",
    "state": "Sumatera Utara",
    "country": "INDONESIA",
    "color": "#41ab5d",
    "count": 1
  },
  {
    "lat": 3.5894617,
    "lon": 98.6741623,
    "failed": false,
    "year": "2023",
    "tablet": "Agapao",
    "city": "Medan",
    "state": "Sumatera Utara",
    "country": "INDONESIA",
    "color": "#41ab5d",
    "count": 1
  },
  {
    "lat": 2.1239421,
    "lon": 99.9894967,
    "failed": false,
    "year": "2024",
    "tablet": "Agapao",
    "city": "Pangkatan",
    "state": "Sumatera Utara",
    "country": "INDONESIA",
    "color": "#41ab5d",
    "count": 1
  },
  {
    "lat": -6.2628908,
    "lon": 106.8822289,
    "failed": false,
    "year": "2023",
    "tablet": "Agapao",
    "city": "Jakarta Timur",
    "state": "DKI Jakarta",
    "country": "INDONESIA",
    "color": "#41ab5d",
    "count": 1
  },
  {
    "lat": 1.7448605,
    "lon": 100.5763381,
    "failed": false,
    "year": "2024",
    "tablet": "Agapao",
    "city": "Bagan Sinembah",
    "state": "Riau",
    "country": "INDONESIA",
    "color": "#41ab5d",
    "count": 1
  },
  {
    "lat": -6.2838694,
    "lon": 106.8048297,
    "failed": false,
    "year": "2023",
    "tablet": "Agapao",
    "city": "Jakarta Selatan",
    "state": "DKI Jakarta",
    "country": "INDONESIA",
    "color": "#41ab5d",
    "count": 1
  },
  {
    "lat": 3.5894617,
    "lon": 98.6741623,
    "failed": false,
    "year": "2024",
    "tablet": "Agapao",
    "city": "Medan",
    "state": "Sumatera Utara",
    "country": "INDONESIA",
    "color": "#41ab5d",
    "count": 1
  },
  {
    "lat": 1.7448605,
    "lon": 100.5763381,
    "failed": false,
    "year": "2023",
    "tablet": "Agapao",
    "city": "Bagan Sinembah",
    "state": "Riau",
    "country": "INDONESIA",
    "color": "#41ab5d",
    "count": 1
  },
  {
    "lat": 3.1168006,
    "lon": 98.1013474,
    "failed": false,
    "year": "2023",
    "tablet": "Agapao",
    "city": "Laubaleng",
    "state": "North Sumatra",
    "country": "INDONESIA",
    "color": "#41ab5d",
    "count": 1
  },
  {
    "lat": 3.5894617,
    "lon": 98.6741623,
    "failed": false,
    "year": "2024",
    "tablet": "Agapao",
    "city": "Medan",
    "state": "Sumatera Utara",
    "country": "INDONESIA",
    "color": "#41ab5d",
    "count": 1
  },
  {
    "lat": 3.5894617,
    "lon": 98.6741623,
    "failed": false,
    "year": "2024",
    "tablet": "Agapao",
    "city": "Medan",
    "state": "Sumatera Utara",
    "country": "INDONESIA",
    "color": "#41ab5d",
    "count": 1
  },
  {
    "lat": -0.3731888,
    "lon": 102.2797084,
    "failed": false,
    "year": "2023",
    "tablet": "Agapao",
    "city": "Air Molek",
    "state": "Riau",
    "country": "INDONESIA",
    "color": "#41ab5d",
    "count": 1
  },
  {
    "lat": 2.260108,
    "lon": 98.7500083,
    "failed": false,
    "year": "2025",
    "tablet": "Agapao",
    "city": "Dolok Sanggul",
    "state": "Sumatera Utara",
    "country": "INDONESIA",
    "color": "#41ab5d",
    "count": 1
  },
  {
    "lat": -6.2628908,
    "lon": 106.8822289,
    "failed": false,
    "year": "2023",
    "tablet": "Agapao",
    "city": "Jakarta Timur",
    "state": "DKI Jakarta",
    "country": "INDONESIA",
    "color": "#41ab5d",
    "count": 1
  },
  {
    "lat": 1.7448605,
    "lon": 100.5763381,
    "failed": false,
    "year": "2024",
    "tablet": "Agapao",
    "city": "Bagan Sinembah",
    "state": "Riau",
    "country": "INDONESIA",
    "color": "#41ab5d",
    "count": 1
  },
  {
    "lat": 0.3854115,
    "lon": 101.8581198,
    "failed": false,
    "year": "2023",
    "tablet": "Agapao",
    "city": "Pangkalan Kerinci",
    "state": "Riau",
    "country": "INDONESIA",
    "color": "#41ab5d",
    "count": 1
  },
  {
    "lat": -6.2628908,
    "lon": 106.8822289,
    "failed": false,
    "year": "2023",
    "tablet": "Agapao",
    "city": "Jakarta Timur",
    "state": "DKI Jakarta",
    "country": "INDONESIA",
    "color": "#41ab5d",
    "count": 1
  },
  {
    "lat": 3.6952434,
    "lon": 98.8310745,
    "failed": false,
    "year": "2023",
    "tablet": "Agapao",
    "city": "Deli Serdang",
    "state": "Sumatera Utara",
    "country": "INDONESIA",
    "color": "#41ab5d",
    "count": 1
  },
  {
    "lat": 3.5894617,
    "lon": 98.6741623,
    "failed": false,
    "year": "2023",
    "tablet": "Agapao",
    "city": "Medan",
    "state": "Sumatera Utara",
    "country": "INDONESIA",
    "color": "#41ab5d",
    "count": 1
  },
  {
    "lat": -2.9888243,
    "lon": 104.7568507,
    "failed": false,
    "year": "2024",
    "tablet": "Agapao",
    "city": "Palembang",
    "state": "Sumatra Selatan",
    "country": "INDONESIA",
    "color": "#41ab5d",
    "count": 1
  },
  {
    "lat": -6.1644013,
    "lon": 106.4679311,
    "failed": false,
    "year": "2023",
    "tablet": "Agapao",
    "city": "Kabupaten Tangerang",
    "state": "Banten",
    "country": "INDONESIA",
    "color": "#41ab5d",
    "count": 1
  },
  {
    "lat": 1.4900578,
    "lon": 124.8408708,
    "failed": false,
    "year": "2024",
    "tablet": "Agapao",
    "city": "Manado",
    "state": "Sulawesi Utara",
    "country": "INDONESIA",
    "color": "#41ab5d",
    "count": 1
  },
  {
    "lat": -0.3731888,
    "lon": 102.2797084,
    "failed": false,
    "year": "2023",
    "tablet": "Agapao",
    "city": "Air Molek",
    "state": "Riau",
    "country": "INDONESIA",
    "color": "#41ab5d",
    "count": 1
  },
  {
    "lat": 3.5894617,
    "lon": 98.6741623,
    "failed": false,
    "year": "2024",
    "tablet": "Agapao",
    "city": "Medan",
    "state": "Sumatera Utara",
    "country": "INDONESIA",
    "color": "#41ab5d",
    "count": 1
  },
  {
    "lat": -8.6524973,
    "lon": 115.2191175,
    "failed": false,
    "year": "2024",
    "tablet": "Agapao",
    "city": "Denpasar",
    "state": "Bali",
    "country": "INDONESIA",
    "color": "#41ab5d",
    "count": 1
  },
  {
    "lat": 3.5894617,
    "lon": 98.6741623,
    "failed": false,
    "year": "2023",
    "tablet": "Agapao",
    "city": "Medan",
    "state": "Sumatera Utara",
    "country": "INDONESIA",
    "color": "#41ab5d",
    "count": 1
  },
  {
    "lat": 2.1239421,
    "lon": 99.9894967,
    "failed": false,
    "year": "2023",
    "tablet": "Agapao",
    "city": "Pangkatan",
    "state": "Sumatera Utara",
    "country": "INDONESIA",
    "color": "#41ab5d",
    "count": 1
  },
  {
    "lat": 3.5894617,
    "lon": 98.6741623,
    "failed": false,
    "year": "2024",
    "tablet": "Agapao",
    "city": "Medan",
    "state": "Sumatera Utara",
    "country": "INDONESIA",
    "color": "#41ab5d",
    "count": 1
  },
  {
    "lat": 1.1603196,
    "lon": 97.6556681,
    "failed": false,
    "year": "2023",
    "tablet": "Agapao",
    "city": "Idanotae",
    "state": "Sumatera Utara",
    "country": "INDONESIA",
    "color": "#41ab5d",
    "count": 1
  },
  {
    "lat": 2.1239421,
    "lon": 99.9894967,
    "failed": false,
    "year": "2024",
    "tablet": "Agapao",
    "city": "Pangkatan",
    "state": "Sumatera Utara",
    "country": "INDONESIA",
    "color": "#41ab5d",
    "count": 1
  },
  {
    "lat": -0.3731888,
    "lon": 102.2797084,
    "failed": false,
    "year": "2023",
    "tablet": "Agapao",
    "city": "Air Molek",
    "state": "Riau",
    "country": "INDONESIA",
    "color": "#41ab5d",
    "count": 1
  },
  {
    "lat": 2.1239421,
    "lon": 99.9894967,
    "failed": false,
    "year": "2023",
    "tablet": "Agapao",
    "city": "Pangkatan",
    "state": "Sumatera Utara",
    "country": "INDONESIA",
    "color": "#41ab5d",
    "count": 1
  },
  {
    "lat": 3.28347,
    "lon": 98.6156331,
    "failed": false,
    "year": "2024",
    "tablet": "Agapao",
    "city": "Mardinding",
    "state": "Sumatera Utara",
    "country": "INDONESIA",
    "color": "#41ab5d",
    "count": 1
  },
  {
    "lat": 3.28347,
    "lon": 98.6156331,
    "failed": false,
    "year": "2024",
    "tablet": "Agapao",
    "city": "Mardinding",
    "state": "Sumatera Utara",
    "country": "INDONESIA",
    "color": "#41ab5d",
    "count": 1
  },
  {
    "lat": 3.1547891,
    "lon": 98.3688115,
    "failed": false,
    "year": "2024",
    "tablet": "Agapao",
    "city": "Mardingding",
    "state": "Sumatera Utara",
    "country": "INDONESIA",
    "color": "#41ab5d",
    "count": 1
  },
  {
    "lat": -0.3731888,
    "lon": 102.2797084,
    "failed": false,
    "year": "2023",
    "tablet": "Agapao",
    "city": "Air Molek",
    "state": "Riau",
    "country": "INDONESIA",
    "color": "#41ab5d",
    "count": 1
  },
  {
    "lat": 1.1030815,
    "lon": 104.0383696,
    "failed": false,
    "year": "2023",
    "tablet": "Agapao",
    "city": "Batam Kota",
    "state": "Kepulauan Riau",
    "country": "INDONESIA",
    "color": "#41ab5d",
    "count": 1
  },
  {
    "lat": -0.3731888,
    "lon": 102.2797084,
    "failed": false,
    "year": "2023",
    "tablet": "Agapao",
    "city": "Air Molek",
    "state": "Riau",
    "country": "INDONESIA",
    "color": "#41ab5d",
    "count": 1
  },
  {
    "lat": 2.1239421,
    "lon": 99.9894967,
    "failed": false,
    "year": "2023",
    "tablet": "Agapao",
    "city": "Pangkatan",
    "state": "Sumatera Utara",
    "country": "INDONESIA",
    "color": "#41ab5d",
    "count": 1
  },
  {
    "lat": 3.5894617,
    "lon": 98.6741623,
    "failed": false,
    "year": "2023",
    "tablet": "Agapao",
    "city": "Medan",
    "state": "Sumatera Utara",
    "country": "INDONESIA",
    "color": "#41ab5d",
    "count": 1
  },
  {
    "lat": 2.1239421,
    "lon": 99.9894967,
    "failed": false,
    "year": "2024",
    "tablet": "Agapao",
    "city": "Pangkatan",
    "state": "Sumatera Utara",
    "country": "INDONESIA",
    "color": "#41ab5d",
    "count": 1
  },
  {
    "lat": -0.3731888,
    "lon": 102.2797084,
    "failed": false,
    "year": "2025",
    "tablet": "Agapao",
    "city": "Air Molek",
    "state": "Riau",
    "country": "INDONESIA",
    "color": "#41ab5d",
    "count": 1
  },
  {
    "lat": -0.3731888,
    "lon": 102.2797084,
    "failed": false,
    "year": "2025",
    "tablet": "Agapao",
    "city": "Air Molek",
    "state": "Riau",
    "country": "INDONESIA",
    "color": "#41ab5d",
    "count": 1
  },
  {
    "lat": -0.3731888,
    "lon": 102.2797084,
    "failed": false,
    "year": "2025",
    "tablet": "Agapao",
    "city": "Air Molek",
    "state": "Riau",
    "country": "INDONESIA",
    "color": "#41ab5d",
    "count": 1
  },
  {
    "lat": 2.1239421,
    "lon": 99.9894967,
    "failed": false,
    "year": "2023",
    "tablet": "Agapao",
    "city": "Pangkatan",
    "state": "Sumatera Utara",
    "country": "INDONESIA",
    "color": "#41ab5d",
    "count": 1
  },
  {
    "lat": 2.1239421,
    "lon": 99.9894967,
    "failed": false,
    "year": "2024",
    "tablet": "Agapao",
    "city": "Pangkatan",
    "state": "Sumatera Utara",
    "country": "INDONESIA",
    "color": "#41ab5d",
    "count": 1
  },
  {
    "lat": 2.3334951,
    "lon": 99.0667621,
    "failed": false,
    "year": "2024",
    "tablet": "Agapao",
    "city": "Balige",
    "state": "Sumatera Utara",
    "country": "INDONESIA",
    "color": "#41ab5d",
    "count": 1
  },
  {
    "lat": 2.260108,
    "lon": 98.7500083,
    "failed": false,
    "year": "2025",
    "tablet": "Agapao",
    "city": "Dolok Sanggul",
    "state": "Sumatera Utara",
    "country": "INDONESIA",
    "color": "#41ab5d",
    "count": 1
  },
  {
    "lat": -6.136197,
    "lon": 106.9006902,
    "failed": false,
    "year": "2025",
    "tablet": "Agapao",
    "city": "Jakarta Utara",
    "state": "DKI Jakarta",
    "country": "INDONESIA",
    "color": "#41ab5d",
    "count": 1
  },
  {
    "lat": -6.2349858,
    "lon": 106.9945444,
    "failed": false,
    "year": "2023",
    "tablet": "Agapao",
    "city": "Bekasi",
    "state": "Jawa Barat",
    "country": "INDONESIA",
    "color": "#41ab5d",
    "count": 1
  },
  {
    "lat": -6.2628908,
    "lon": 106.8822289,
    "failed": false,
    "year": "2023",
    "tablet": "Agapao",
    "city": "Jakarta Timur",
    "state": "DKI Jakarta",
    "country": "INDONESIA",
    "color": "#41ab5d",
    "count": 1
  },
  {
    "lat": -6.18234,
    "lon": 106.8428715,
    "failed": false,
    "year": "2024",
    "tablet": "Agapao",
    "city": "Jakarta Pusat",
    "state": "DKI Jakarta",
    "country": "INDONESIA",
    "color": "#41ab5d",
    "count": 1
  },
  {
    "lat": -6.2349858,
    "lon": 106.9945444,
    "failed": false,
    "year": "2023",
    "tablet": "Agapao",
    "city": "Bekasi",
    "state": "Jawa Barat",
    "country": "INDONESIA",
    "color": "#41ab5d",
    "count": 1
  },
  {
    "lat": 3.5894617,
    "lon": 98.6741623,
    "failed": false,
    "year": "2023",
    "tablet": "Agapao",
    "city": "Medan",
    "state": "Sumatera Utara",
    "country": "INDONESIA",
    "color": "#41ab5d",
    "count": 1
  },
  {
    "lat": -6.2838694,
    "lon": 106.8048297,
    "failed": false,
    "year": "2023",
    "tablet": "Agapao",
    "city": "Jakarta Selatan",
    "state": "DKI Jakarta",
    "country": "INDONESIA",
    "color": "#41ab5d",
    "count": 1
  },
  {
    "lat": -2.4833826,
    "lon": 117.8902853,
    "failed": true,
    "year": "2024",
    "tablet": "Agapao",
    "city": "Kecamatan Parmaksian",
    "state": "North Sumatra",
    "country": "INDONESIA",
    "color": "#FF0000",
    "count": 1
  },
  {
    "lat": 1.742118,
    "lon": 100.3029023,
    "failed": false,
    "year": "2023",
    "tablet": "Agapao",
    "city": "Torgamba",
    "state": "Sumatera Utara",
    "country": "INDONESIA",
    "color": "#41ab5d",
    "count": 1
  },
  {
    "lat": 2.1239421,
    "lon": 99.9894967,
    "failed": false,
    "year": "2024",
    "tablet": "Agapao",
    "city": "Pangkatan",
    "state": "Sumatera Utara",
    "country": "INDONESIA",
    "color": "#41ab5d",
    "count": 1
  },
  {
    "lat": -4.3980264,
    "lon": 105.5542801,
    "failed": false,
    "year": "2023",
    "tablet": "Agapao",
    "city": "Tulang Bawang",
    "state": "Lampung",
    "country": "INDONESIA",
    "color": "#41ab5d",
    "count": 1
  },
  {
    "lat": 2.1239421,
    "lon": 99.9894967,
    "failed": false,
    "year": "2023",
    "tablet": "Agapao",
    "city": "Pangkatan",
    "state": "Sumatra Utara",
    "country": "INDONESIA",
    "color": "#41ab5d",
    "count": 1
  },
  {
    "lat": -0.3731888,
    "lon": 102.2797084,
    "failed": false,
    "year": "2025",
    "tablet": "Agapao",
    "city": "Air Molek",
    "state": "Riau",
    "country": "INDONESIA",
    "color": "#41ab5d",
    "count": 1
  },
  {
    "lat": 2.1239421,
    "lon": 99.9894967,
    "failed": false,
    "year": "2024",
    "tablet": "Agapao",
    "city": "Pangkatan",
    "state": "Sumatera Utara",
    "country": "INDONESIA",
    "color": "#41ab5d",
    "count": 1
  },
  {
    "lat": 3.5894617,
    "lon": 98.6741623,
    "failed": false,
    "year": "2024",
    "tablet": "Agapao",
    "city": "Medan",
    "state": "Sumatera Utara",
    "country": "INDONESIA",
    "color": "#41ab5d",
    "count": 1
  },
  {
    "lat": -0.3731888,
    "lon": 102.2797084,
    "failed": false,
    "year": "2023",
    "tablet": "Agapao",
    "city": "Air Molek",
    "state": "Riau",
    "country": "INDONESIA",
    "color": "#41ab5d",
    "count": 1
  },
  {
    "lat": 3.5894617,
    "lon": 98.6741623,
    "failed": false,
    "year": "2023",
    "tablet": "Agapao",
    "city": "Medan",
    "state": "Sumatera Utara",
    "country": "INDONESIA",
    "color": "#41ab5d",
    "count": 1
  },
  {
    "lat": 0.5262455,
    "lon": 101.4515727,
    "failed": false,
    "year": "2024",
    "tablet": "Agapao",
    "city": "Pekan Baru",
    "state": "Riau",
    "country": "INDONESIA",
    "color": "#41ab5d",
    "count": 1
  },
  {
    "lat": 3.6952434,
    "lon": 98.8310745,
    "failed": false,
    "year": "2023",
    "tablet": "Agapao",
    "city": "Deli Serdang",
    "state": "Sumatera Utara",
    "country": "INDONESIA",
    "color": "#41ab5d",
    "count": 1
  },
  {
    "lat": 3.5894617,
    "lon": 98.6741623,
    "failed": false,
    "year": "2024",
    "tablet": "Agapao",
    "city": "Medan",
    "state": "Sumatera Utara",
    "country": "INDONESIA",
    "color": "#41ab5d",
    "count": 1
  },
  {
    "lat": -6.2628908,
    "lon": 106.8822289,
    "failed": false,
    "year": "2023",
    "tablet": "Agapao",
    "city": "Jakarta Timur",
    "state": "DKI Jakarta",
    "country": "INDONESIA",
    "color": "#41ab5d",
    "count": 1
  },
  {
    "lat": 1.7448605,
    "lon": 100.5763381,
    "failed": false,
    "year": "2024",
    "tablet": "Agapao",
    "city": "Bagan Sinembah",
    "state": "Riau",
    "country": "INDONESIA",
    "color": "#41ab5d",
    "count": 1
  },
  {
    "lat": -6.2628908,
    "lon": 106.8822289,
    "failed": false,
    "year": "2023",
    "tablet": "Agapao",
    "city": "Jakarta Timur",
    "state": "DKI Jakarta",
    "country": "INDONESIA",
    "color": "#41ab5d",
    "count": 1
  },
  {
    "lat": 3.5894617,
    "lon": 98.6741623,
    "failed": false,
    "year": "2024",
    "tablet": "Agapao",
    "city": "Medan",
    "state": "Sumatera Utara",
    "country": "INDONESIA",
    "color": "#41ab5d",
    "count": 1
  },
  {
    "lat": 3.7170618,
    "lon": 98.6928173,
    "failed": false,
    "year": "2024",
    "tablet": "Agapao",
    "city": "Medan Labuhan",
    "state": "Sumatera Utara",
    "country": "INDONESIA",
    "color": "#41ab5d",
    "count": 1
  },
  {
    "lat": 3.9074565,
    "lon": 117.0423506,
    "failed": false,
    "year": "2023",
    "tablet": "Agapao",
    "city": "Nunukan",
    "state": "Kalimantan Utara",
    "country": "INDONESIA",
    "color": "#41ab5d",
    "count": 1
  },
  {
    "lat": -6.2628908,
    "lon": 106.8822289,
    "failed": false,
    "year": "2023",
    "tablet": "Agapao",
    "city": "Jakarta Timur",
    "state": "DKI Jakarta",
    "country": "INDONESIA",
    "color": "#41ab5d",
    "count": 1
  },
  {
    "lat": 0.3854115,
    "lon": 101.8581198,
    "failed": false,
    "year": "2023",
    "tablet": "Agapao",
    "city": "Pangkalan Kerinci",
    "state": "Riau",
    "country": "INDONESIA",
    "color": "#41ab5d",
    "count": 1
  },
  {
    "lat": 2.1239421,
    "lon": 99.9894967,
    "failed": false,
    "year": "2024",
    "tablet": "Agapao",
    "city": "Pangkatan",
    "state": "Sumatera Utara",
    "country": "INDONESIA",
    "color": "#41ab5d",
    "count": 1
  },
  {
    "lat": 0.3854115,
    "lon": 101.8581198,
    "failed": false,
    "year": "2024",
    "tablet": "Agapao",
    "city": "Pangkalan Kerinci",
    "state": "Riau",
    "country": "INDONESIA",
    "color": "#41ab5d",
    "count": 1
  },
  {
    "lat": 3.5894617,
    "lon": 98.6741623,
    "failed": false,
    "year": "2023",
    "tablet": "Agapao",
    "city": "Medan",
    "state": "Sumatera Utara",
    "country": "INDONESIA",
    "color": "#41ab5d",
    "count": 1
  },
  {
    "lat": -6.1761924,
    "lon": 106.6382161,
    "failed": false,
    "year": "2023",
    "tablet": "Agapao",
    "city": "Tangerang",
    "state": "Banten",
    "country": "INDONESIA",
    "color": "#41ab5d",
    "count": 1
  },
  {
    "lat": -6.1761924,
    "lon": 106.6382161,
    "failed": false,
    "year": "2025",
    "tablet": "Agapao",
    "city": "Kota Tangerang",
    "state": "Banten",
    "country": "INDONESIA",
    "color": "#41ab5d",
    "count": 1
  },
  {
    "lat": 2.8503551,
    "lon": 98.5250473,
    "failed": false,
    "year": "2023",
    "tablet": "Agapao",
    "city": "Paropo",
    "state": "Sumatera Utara",
    "country": "INDONESIA",
    "color": "#41ab5d",
    "count": 1
  },
  {
    "lat": 2.8503551,
    "lon": 98.5250473,
    "failed": false,
    "year": "2023",
    "tablet": "Agapao",
    "city": "Paropo",
    "state": "Sumatera Utara",
    "country": "INDONESIA",
    "color": "#41ab5d",
    "count": 1
  },
  {
    "lat": -6.017389,
    "lon": 106.0537688,
    "failed": false,
    "year": "2023",
    "tablet": "Agapao",
    "city": "Kota Cilegon",
    "state": "Banten",
    "country": "INDONESIA",
    "color": "#41ab5d",
    "count": 1
  },
  {
    "lat": -6.136197,
    "lon": 106.9006902,
    "failed": false,
    "year": "2023",
    "tablet": "Agapao",
    "city": "Jakarta Utara",
    "state": "DKI Jakarta",
    "country": "INDONESIA",
    "color": "#41ab5d",
    "count": 1
  },
  {
    "lat": 2.260108,
    "lon": 98.7500083,
    "failed": false,
    "year": "2024",
    "tablet": "Agapao",
    "city": "Dolok Sanggul",
    "state": "Sumatera Utara",
    "country": "INDONESIA",
    "color": "#41ab5d",
    "count": 1
  },
  {
    "lat": 3.5894617,
    "lon": 98.6741623,
    "failed": false,
    "year": "2023",
    "tablet": "Agapao",
    "city": "Medan",
    "state": "Sumatera Utara",
    "country": "INDONESIA",
    "color": "#41ab5d",
    "count": 1
  },
  {
    "lat": 2.260108,
    "lon": 98.7500083,
    "failed": false,
    "year": "2025",
    "tablet": "Agapao",
    "city": "Dolok Sanggul",
    "state": "Sumatera Utara",
    "country": "INDONESIA",
    "color": "#41ab5d",
    "count": 1
  },
  {
    "lat": 2.260108,
    "lon": 98.7500083,
    "failed": false,
    "year": "2025",
    "tablet": "Agapao",
    "city": "Dolok Sanggul",
    "state": "Sumatera Utara",
    "country": "INDONESIA",
    "color": "#41ab5d",
    "count": 1
  },
  {
    "lat": -2.9888243,
    "lon": 104.7568507,
    "failed": false,
    "year": "2024",
    "tablet": "Agapao",
    "city": "Palembang",
    "state": "Sumatera Selatan",
    "country": "INDONESIA",
    "color": "#41ab5d",
    "count": 1
  },
  {
    "lat": 3.5894617,
    "lon": 98.6741623,
    "failed": false,
    "year": "2024",
    "tablet": "Agapao",
    "city": "Medan",
    "state": "Sumatera Utara",
    "country": "INDONESIA",
    "color": "#41ab5d",
    "count": 1
  },
  {
    "lat": 3.5894617,
    "lon": 98.6741623,
    "failed": false,
    "year": "2024",
    "tablet": "Agapao",
    "city": "Medan",
    "state": "Sumatera Utara",
    "country": "INDONESIA",
    "color": "#41ab5d",
    "count": 1
  },
  {
    "lat": 2.6715649,
    "lon": 98.9915713,
    "failed": false,
    "year": "2024",
    "tablet": "Agapao",
    "city": "Girsang Sipangan Bolon",
    "state": "North Sumatra",
    "country": "INDONESIA",
    "color": "#41ab5d",
    "count": 1
  },
  {
    "lat": 3.5894617,
    "lon": 98.6741623,
    "failed": false,
    "year": "2024",
    "tablet": "Agapao",
    "city": "Medan",
    "state": "Sumatera Utara",
    "country": "INDONESIA",
    "color": "#41ab5d",
    "count": 1
  },
  {
    "lat": -0.3731888,
    "lon": 102.2797084,
    "failed": false,
    "year": "2023",
    "tablet": "Agapao",
    "city": "Air Molek",
    "state": "Riau",
    "country": "INDONESIA",
    "color": "#41ab5d",
    "count": 1
  },
  {
    "lat": 3.1547891,
    "lon": 98.3688115,
    "failed": false,
    "year": "2023",
    "tablet": "Agapao",
    "city": "Mardingding",
    "state": "Sumatera Utara",
    "country": "INDONESIA",
    "color": "#41ab5d",
    "count": 1
  },
  {
    "lat": 3.1547891,
    "lon": 98.3688115,
    "failed": false,
    "year": "2023",
    "tablet": "Agapao",
    "city": "Mardingding",
    "state": "Sumatera Utara",
    "country": "INDONESIA",
    "color": "#41ab5d",
    "count": 1
  },
  {
    "lat": -6.2628908,
    "lon": 106.8822289,
    "failed": false,
    "year": "2023",
    "tablet": "Agapao",
    "city": "Jakarta Timur",
    "state": "DKI Jakarta",
    "country": "INDONESIA",
    "color": "#41ab5d",
    "count": 1
  },
  {
    "lat": -2.4833826,
    "lon": 117.8902853,
    "failed": true,
    "year": "2023",
    "tablet": "Agapao",
    "city": "Dolok Huluan",
    "state": "North Sumatra",
    "country": "INDONESIA",
    "color": "#FF0000",
    "count": 1
  },
  {
    "lat": 3.5894617,
    "lon": 98.6741623,
    "failed": false,
    "year": "2024",
    "tablet": "Agapao",
    "city": "Medan",
    "state": "Sumatera Utara",
    "country": "INDONESIA",
    "color": "#41ab5d",
    "count": 1
  },
  {
    "lat": -6.2628908,
    "lon": 106.8822289,
    "failed": false,
    "year": "2023",
    "tablet": "Agapao",
    "city": "Jakarta Timur",
    "state": "DKI Jakarta",
    "country": "INDONESIA",
    "color": "#41ab5d",
    "count": 1
  },
  {
    "lat": -6.2628908,
    "lon": 106.8822289,
    "failed": false,
    "year": "2023",
    "tablet": "Agapao",
    "city": "Jakarta Timur",
    "state": "DKI Jakarta",
    "country": "INDONESIA",
    "color": "#41ab5d",
    "count": 1
  },
  {
    "lat": 3.6952434,
    "lon": 98.8310745,
    "failed": false,
    "year": "2023",
    "tablet": "Agapao",
    "city": "Deli Serdang",
    "state": "Sumatera Utara",
    "country": "INDONESIA",
    "color": "#41ab5d",
    "count": 1
  },
  {
    "lat": -2.4833826,
    "lon": 117.8902853,
    "failed": true,
    "year": "2024",
    "tablet": "Agapao",
    "city": "Kecamatan Parmaksian",
    "state": "North Sumatra",
    "country": "INDONESIA",
    "color": "#FF0000",
    "count": 1
  },
  {
    "lat": -7.6290837,
    "lon": 111.5168819,
    "failed": false,
    "year": "2023",
    "tablet": "Agapao",
    "city": "Madiun",
    "state": "Jawa Timur",
    "country": "INDONESIA",
    "color": "#41ab5d",
    "count": 1
  },
  {
    "lat": -6.2628908,
    "lon": 106.8822289,
    "failed": false,
    "year": "2023",
    "tablet": "Agapao",
    "city": "Jakarta Timur",
    "state": "DKI Jakarta",
    "country": "INDONESIA",
    "color": "#41ab5d",
    "count": 1
  },
  {
    "lat": 3.5894617,
    "lon": 98.6741623,
    "failed": false,
    "year": "2023",
    "tablet": "Agapao",
    "city": "Medan",
    "state": "Sumatera Utara",
    "country": "INDONESIA",
    "color": "#41ab5d",
    "count": 1
  },
  {
    "lat": 0.1302785,
    "lon": 102.0736516,
    "failed": false,
    "year": "2023",
    "tablet": "Agapao",
    "city": "Sorek",
    "state": "Riau",
    "country": "INDONESIA",
    "color": "#41ab5d",
    "count": 1
  },
  {
    "lat": 3.5894617,
    "lon": 98.6741623,
    "failed": false,
    "year": "2023",
    "tablet": "Agapao",
    "city": "Medan",
    "state": "Sumatera Utara",
    "country": "INDONESIA",
    "color": "#41ab5d",
    "count": 1
  },
  {
    "lat": 0.1308913,
    "lon": 102.0736142,
    "failed": false,
    "year": "2023",
    "tablet": "Agapao",
    "city": "Sorek Satu",
    "state": "Riau",
    "country": "INDONESIA",
    "color": "#41ab5d",
    "count": 1
  },
  {
    "lat": -2.9880341,
    "lon": 104.7475801,
    "failed": false,
    "year": "2024",
    "tablet": "Agapao",
    "city": "Oki",
    "state": "Sumatera Selatan",
    "country": "INDONESIA",
    "color": "#41ab5d",
    "count": 1
  },
  {
    "lat": -8.5566523,
    "lon": 115.0013121,
    "failed": false,
    "year": "2024",
    "tablet": "Agapao",
    "city": "Tabanan",
    "state": "Bali",
    "country": "INDONESIA",
    "color": "#41ab5d",
    "count": 1
  },
  {
    "lat": 2.1239421,
    "lon": 99.9894967,
    "failed": false,
    "year": "2023",
    "tablet": "Agapao",
    "city": "Pangkatan",
    "state": "Sumatera Utara",
    "country": "INDONESIA",
    "color": "#41ab5d",
    "count": 1
  },
  {
    "lat": -7.6290837,
    "lon": 111.5168819,
    "failed": false,
    "year": "2023",
    "tablet": "Agapao",
    "city": "Madiun",
    "state": "Jawa Timur",
    "country": "INDONESIA",
    "color": "#41ab5d",
    "count": 1
  },
  {
    "lat": 3.5894617,
    "lon": 98.6741623,
    "failed": false,
    "year": "2024",
    "tablet": "Agapao",
    "city": "Medan",
    "state": "Sumatera utara",
    "country": "INDONESIA",
    "color": "#41ab5d",
    "count": 1
  },
  {
    "lat": 3.5894617,
    "lon": 98.6741623,
    "failed": false,
    "year": "2024",
    "tablet": "Agapao",
    "city": "Medan",
    "state": "Sumatera Utara",
    "country": "INDONESIA",
    "color": "#41ab5d",
    "count": 1
  },
  {
    "lat": 2.9505161,
    "lon": 98.7835306,
    "failed": false,
    "year": "2025",
    "tablet": "Agapao",
    "city": "Simalungun",
    "state": "Sumatera Utara",
    "country": "INDONESIA",
    "color": "#41ab5d",
    "count": 1
  },
  {
    "lat": 3.5894617,
    "lon": 98.6741623,
    "failed": false,
    "year": "2024",
    "tablet": "Agapao",
    "city": "Medan",
    "state": "Sumatera Utara",
    "country": "INDONESIA",
    "color": "#41ab5d",
    "count": 1
  },
  {
    "lat": 3.5894617,
    "lon": 98.6741623,
    "failed": false,
    "year": "2024",
    "tablet": "Agapao",
    "city": "Medan",
    "state": "Sumatera Utara",
    "country": "INDONESIA",
    "color": "#41ab5d",
    "count": 1
  },
  {
    "lat": -6.2628908,
    "lon": 106.8822289,
    "failed": false,
    "year": "2023",
    "tablet": "Agapao",
    "city": "Jakarta Timur",
    "state": "DKI Jakarta",
    "country": "INDONESIA",
    "color": "#41ab5d",
    "count": 1
  },
  {
    "lat": 2.9877971,
    "lon": 98.4406927,
    "failed": false,
    "year": "<NA>",
    "tablet": "Agapao",
    "city": "Tanah Karo",
    "state": "Sumatera Utara",
    "country": "INDONESIA",
    "color": "#41ab5d",
    "count": 1
  },
  {
    "lat": -7.6290837,
    "lon": 111.5168819,
    "failed": false,
    "year": "2023",
    "tablet": "Agapao",
    "city": "Madiun",
    "state": "Jawa Timur",
    "country": "INDONESIA",
    "color": "#41ab5d",
    "count": 1
  },
  {
    "lat": 2.0541345,
    "lon": 100.1428891,
    "failed": false,
    "year": "2024",
    "tablet": "Agapao",
    "city": "Kampung Rakyat",
    "state": "Sumatera Utara",
    "country": "INDONESIA",
    "color": "#41ab5d",
    "count": 1
  },
  {
    "lat": -6.2628908,
    "lon": 106.8822289,
    "failed": false,
    "year": "2023",
    "tablet": "Agapao",
    "city": "Jakarta Timur",
    "state": "DKI Jakarta",
    "country": "INDONESIA",
    "color": "#41ab5d",
    "count": 1
  },
  {
    "lat": 3.5894617,
    "lon": 98.6741623,
    "failed": false,
    "year": "2023",
    "tablet": "Agapao",
    "city": "Medan",
    "state": "Sumatera Utara",
    "country": "INDONESIA",
    "color": "#41ab5d",
    "count": 1
  },
  {
    "lat": -1.7070411,
    "lon": 103.7875144,
    "failed": false,
    "year": "2023",
    "tablet": "Agapao",
    "city": "Muaro Jambi",
    "state": "Jambi",
    "country": "INDONESIA",
    "color": "#41ab5d",
    "count": 1
  },
  {
    "lat": -0.3731888,
    "lon": 102.2797084,
    "failed": false,
    "year": "2023",
    "tablet": "Agapao",
    "city": "Air Molek",
    "state": "Riau",
    "country": "INDONESIA",
    "color": "#41ab5d",
    "count": 1
  },
  {
    "lat": -2.4833826,
    "lon": 117.8902853,
    "failed": true,
    "year": "2023",
    "tablet": "Agapao",
    "city": "Kecamatan Siantar",
    "state": "North Sumatra",
    "country": "INDONESIA",
    "color": "#FF0000",
    "count": 1
  },
  {
    "lat": 2.1239421,
    "lon": 99.9894967,
    "failed": false,
    "year": "2023",
    "tablet": "Agapao",
    "city": "Pangkatan",
    "state": "Sumatera Utara",
    "country": "INDONESIA",
    "color": "#41ab5d",
    "count": 1
  },
  {
    "lat": 3.6952434,
    "lon": 98.8310745,
    "failed": false,
    "year": "2023",
    "tablet": "Agapao",
    "city": "Deli Serdang",
    "state": "Sumatera Utara",
    "country": "INDONESIA",
    "color": "#41ab5d",
    "count": 1
  },
  {
    "lat": 3.1168006,
    "lon": 98.1013474,
    "failed": false,
    "year": "2023",
    "tablet": "Agapao",
    "city": "Laubaleng",
    "state": "North Sumatra",
    "country": "INDONESIA",
    "color": "#41ab5d",
    "count": 1
  },
  {
    "lat": 2.1239421,
    "lon": 99.9894967,
    "failed": false,
    "year": "2023",
    "tablet": "Agapao",
    "city": "Pangkatan",
    "state": "Sumatera Utara",
    "country": "INDONESIA",
    "color": "#41ab5d",
    "count": 1
  },
  {
    "lat": 3.5894617,
    "lon": 98.6741623,
    "failed": false,
    "year": "2023",
    "tablet": "Agapao",
    "city": "Medan",
    "state": "Sumatra Utara",
    "country": "INDONESIA",
    "color": "#41ab5d",
    "count": 1
  },
  {
    "lat": 3.5894617,
    "lon": 98.6741623,
    "failed": false,
    "year": "2023",
    "tablet": "Agapao",
    "city": "Medan",
    "state": "Sumatera Utara",
    "country": "INDONESIA",
    "color": "#41ab5d",
    "count": 1
  },
  {
    "lat": 3.5894617,
    "lon": 98.6741623,
    "failed": false,
    "year": "2023",
    "tablet": "Agapao",
    "city": "Medan",
    "state": "Sumatera Utara",
    "country": "INDONESIA",
    "color": "#41ab5d",
    "count": 1
  },
  {
    "lat": 3.1168006,
    "lon": 98.1013474,
    "failed": false,
    "year": "2024",
    "tablet": "Agapao",
    "city": "Laubaleng",
    "state": "North Sumatra",
    "country": "INDONESIA",
    "color": "#41ab5d",
    "count": 1
  },
  {
    "lat": -6.2628908,
    "lon": 106.8822289,
    "failed": false,
    "year": "2023",
    "tablet": "Agapao",
    "city": "Jakarta Timur",
    "state": "DKI Jakarta",
    "country": "INDONESIA",
    "color": "#41ab5d",
    "count": 1
  },
  {
    "lat": 3.5894617,
    "lon": 98.6741623,
    "failed": false,
    "year": "2023",
    "tablet": "Agapao",
    "city": "Medan",
    "state": "Sumatera Utara",
    "country": "INDONESIA",
    "color": "#41ab5d",
    "count": 1
  },
  {
    "lat": -6.2628908,
    "lon": 106.8822289,
    "failed": false,
    "year": "2023",
    "tablet": "Agapao",
    "city": "Jakarta Timur",
    "state": "DKI Jakarta",
    "country": "INDONESIA",
    "color": "#41ab5d",
    "count": 1
  },
  {
    "lat": 1.7448605,
    "lon": 100.5763381,
    "failed": false,
    "year": "2024",
    "tablet": "Agapao",
    "city": "Bagan Sinembah",
    "state": "Riau",
    "country": "INDONESIA",
    "color": "#41ab5d",
    "count": 1
  },
  {
    "lat": 3.5894617,
    "lon": 98.6741623,
    "failed": false,
    "year": "2023",
    "tablet": "Agapao",
    "city": "Medan",
    "state": "Sumatera Utara",
    "country": "INDONESIA",
    "color": "#41ab5d",
    "count": 1
  },
  {
    "lat": -6.2628908,
    "lon": 106.8822289,
    "failed": false,
    "year": "2024",
    "tablet": "Agapao",
    "city": "Jakarta Timur",
    "state": "DKI Jakarta",
    "country": "INDONESIA",
    "color": "#41ab5d",
    "count": 1
  },
  {
    "lat": 3.6952434,
    "lon": 98.8310745,
    "failed": false,
    "year": "2024",
    "tablet": "Agapao",
    "city": "Deli Serdang",
    "state": "Sumatera Utara",
    "country": "INDONESIA",
    "color": "#41ab5d",
    "count": 1
  },
  {
    "lat": 1.9980604,
    "lon": 99.0647659,
    "failed": false,
    "year": "2023",
    "tablet": "Agapao",
    "city": "Tapanuli Utara",
    "state": "Sumatera Utara",
    "country": "INDONESIA",
    "color": "#41ab5d",
    "count": 1
  },
  {
    "lat": -6.1761924,
    "lon": 106.6382161,
    "failed": false,
    "year": "2023",
    "tablet": "Agapao",
    "city": "Tangerang",
    "state": "Banten",
    "country": "INDONESIA",
    "color": "#41ab5d",
    "count": 1
  },
  {
    "lat": 2.1239421,
    "lon": 99.9894967,
    "failed": false,
    "year": "2024",
    "tablet": "Agapao",
    "city": "Pangkatan",
    "state": "Sumatera Utara",
    "country": "INDONESIA",
    "color": "#41ab5d",
    "count": 1
  },
  {
    "lat": -1.6953637,
    "lon": 103.7161941,
    "failed": false,
    "year": "2023",
    "tablet": "Agapao",
    "city": "Sungai Gelam",
    "state": "Jambi",
    "country": "INDONESIA",
    "color": "#41ab5d",
    "count": 1
  },
  {
    "lat": 3.5894617,
    "lon": 98.6741623,
    "failed": false,
    "year": "2023",
    "tablet": "Agapao",
    "city": "Medan",
    "state": "Sumatera Utara",
    "country": "INDONESIA",
    "color": "#41ab5d",
    "count": 1
  },
  {
    "lat": -6.2628908,
    "lon": 106.8822289,
    "failed": false,
    "year": "2023",
    "tablet": "Agapao",
    "city": "Jakarta Timur",
    "state": "DKI Jakarta",
    "country": "INDONESIA",
    "color": "#41ab5d",
    "count": 1
  },
  {
    "lat": 0.1302785,
    "lon": 102.0736516,
    "failed": false,
    "year": "2023",
    "tablet": "Agapao",
    "city": "Sorek",
    "state": "Riau",
    "country": "INDONESIA",
    "color": "#41ab5d",
    "count": 1
  },
  {
    "lat": 3.5894617,
    "lon": 98.6741623,
    "failed": false,
    "year": "2023",
    "tablet": "Agapao",
    "city": "Medan",
    "state": "Sumatera Utara",
    "country": "INDONESIA",
    "color": "#41ab5d",
    "count": 1
  },
  {
    "lat": 3.5894617,
    "lon": 98.6741623,
    "failed": false,
    "year": "2023",
    "tablet": "Agapao",
    "city": "Medan",
    "state": "Sumatera Utara",
    "country": "INDONESIA",
    "color": "#41ab5d",
    "count": 1
  },
  {
    "lat": -6.2628908,
    "lon": 106.8822289,
    "failed": false,
    "year": "2023",
    "tablet": "Agapao",
    "city": "Jakarta Timur",
    "state": "DKI Jakarta",
    "country": "INDONESIA",
    "color": "#41ab5d",
    "count": 1
  },
  {
    "lat": 2.260108,
    "lon": 98.7500083,
    "failed": false,
    "year": "2025",
    "tablet": "Agapao",
    "city": "Dolok Sanggul",
    "state": "Sumatera Utara",
    "country": "INDONESIA",
    "color": "#41ab5d",
    "count": 1
  },
  {
    "lat": -6.2628908,
    "lon": 106.8822289,
    "failed": false,
    "year": "2024",
    "tablet": "Agapao",
    "city": "Jakarta Timur",
    "state": "DKI Jakarta",
    "country": "INDONESIA",
    "color": "#41ab5d",
    "count": 1
  },
  {
    "lat": 1.367076,
    "lon": 99.2725472,
    "failed": false,
    "year": "2023",
    "tablet": "Agapao",
    "city": "Raya",
    "state": "Sumatera Utara",
    "country": "INDONESIA",
    "color": "#41ab5d",
    "count": 1
  },
  {
    "lat": -6.2628908,
    "lon": 106.8822289,
    "failed": false,
    "year": "2023",
    "tablet": "Agapao",
    "city": "Jakarta Timur",
    "state": "DKI Jakarta",
    "country": "INDONESIA",
    "color": "#41ab5d",
    "count": 1
  },
  {
    "lat": 3.5894617,
    "lon": 98.6741623,
    "failed": false,
    "year": "2024",
    "tablet": "Agapao",
    "city": "Medan",
    "state": "Sumatera Utara",
    "country": "INDONESIA",
    "color": "#41ab5d",
    "count": 1
  },
  {
    "lat": 2.9505161,
    "lon": 98.7835306,
    "failed": false,
    "year": "2025",
    "tablet": "Agapao",
    "city": "Simalungun",
    "state": "Sumatera Utara",
    "country": "INDONESIA",
    "color": "#41ab5d",
    "count": 1
  },
  {
    "lat": -6.2553138,
    "lon": 107.1450733,
    "failed": false,
    "year": "2024",
    "tablet": "Agapao",
    "city": "Cikarang",
    "state": "Jawa Barat",
    "country": "INDONESIA",
    "color": "#41ab5d",
    "count": 1
  },
  {
    "lat": 3.5894617,
    "lon": 98.6741623,
    "failed": false,
    "year": "2023",
    "tablet": "Agapao",
    "city": "Medan",
    "state": "Sumatera Utara",
    "country": "INDONESIA",
    "color": "#41ab5d",
    "count": 1
  },
  {
    "lat": 3.5894617,
    "lon": 98.6741623,
    "failed": false,
    "year": "2023",
    "tablet": "Agapao",
    "city": "Medan",
    "state": "Sumatera Utara",
    "country": "INDONESIA",
    "color": "#41ab5d",
    "count": 1
  },
  {
    "lat": 3.5894617,
    "lon": 98.6741623,
    "failed": false,
    "year": "2024",
    "tablet": "Agapao",
    "city": "Medan",
    "state": "Sumatera Utara",
    "country": "INDONESIA",
    "color": "#41ab5d",
    "count": 1
  },
  {
    "lat": 3.5894617,
    "lon": 98.6741623,
    "failed": false,
    "year": "2023",
    "tablet": "Agapao",
    "city": "Medan",
    "state": "Sumatera Utara",
    "country": "INDONESIA",
    "color": "#41ab5d",
    "count": 1
  },
  {
    "lat": -6.2628908,
    "lon": 106.8822289,
    "failed": false,
    "year": "2023",
    "tablet": "Agapao",
    "city": "Jakarta Timur",
    "state": "DKI Jakarta",
    "country": "INDONESIA",
    "color": "#41ab5d",
    "count": 1
  },
  {
    "lat": 3.1168006,
    "lon": 98.1013474,
    "failed": false,
    "year": "2024",
    "tablet": "Agapao",
    "city": "Laubaleng",
    "state": "North Sumatra",
    "country": "INDONESIA",
    "color": "#41ab5d",
    "count": 1
  },
  {
    "lat": 0.1302785,
    "lon": 102.0736516,
    "failed": false,
    "year": "2023",
    "tablet": "Agapao",
    "city": "Sorek",
    "state": "Riau",
    "country": "INDONESIA",
    "color": "#41ab5d",
    "count": 1
  },
  {
    "lat": 2.1239421,
    "lon": 99.9894967,
    "failed": false,
    "year": "2024",
    "tablet": "Agapao",
    "city": "Pangkatan",
    "state": "Sumatera Utara",
    "country": "INDONESIA",
    "color": "#41ab5d",
    "count": 1
  },
  {
    "lat": 3.0998751,
    "lon": 98.3369706,
    "failed": false,
    "year": "2024",
    "tablet": "Agapao",
    "city": "Karo",
    "state": "Sumatra Utara",
    "country": "INDONESIA",
    "color": "#41ab5d",
    "count": 1
  },
  {
    "lat": -2.9888243,
    "lon": 104.7568507,
    "failed": false,
    "year": "2023",
    "tablet": "Agapao",
    "city": "Palembang",
    "state": "Sumatera Selatan",
    "country": "INDONESIA",
    "color": "#41ab5d",
    "count": 1
  },
  {
    "lat": 3.5894617,
    "lon": 98.6741623,
    "failed": false,
    "year": "2023",
    "tablet": "Agapao",
    "city": "Medan",
    "state": "Sumatera Utara",
    "country": "INDONESIA",
    "color": "#41ab5d",
    "count": 1
  },
  {
    "lat": 3.6063964,
    "lon": 98.4899865,
    "failed": false,
    "year": "2023",
    "tablet": "Agapao",
    "city": "Binjai",
    "state": "Sumatera Utara",
    "country": "INDONESIA",
    "color": "#41ab5d",
    "count": 1
  },
  {
    "lat": 2.1239421,
    "lon": 99.9894967,
    "failed": false,
    "year": "2023",
    "tablet": "Agapao",
    "city": "Pangkatan",
    "state": "Sumatera Utara",
    "country": "INDONESIA",
    "color": "#41ab5d",
    "count": 1
  },
  {
    "lat": -6.2349858,
    "lon": 106.9945444,
    "failed": false,
    "year": "2024",
    "tablet": "Agapao",
    "city": "Bekasi",
    "state": "Jawa Barat",
    "country": "INDONESIA",
    "color": "#41ab5d",
    "count": 1
  },
  {
    "lat": -0.3731888,
    "lon": 102.2797084,
    "failed": false,
    "year": "2025",
    "tablet": "Agapao",
    "city": "Air Molek",
    "state": "Riau",
    "country": "INDONESIA",
    "color": "#41ab5d",
    "count": 1
  },
  {
    "lat": 0.7833163,
    "lon": 101.4597196,
    "failed": false,
    "year": "2023",
    "tablet": "Agapao",
    "city": "Minas",
    "state": "Riau",
    "country": "INDONESIA",
    "color": "#41ab5d",
    "count": 1
  },
  {
    "lat": 3.5894617,
    "lon": 98.6741623,
    "failed": false,
    "year": "2023",
    "tablet": "Agapao",
    "city": "Medan",
    "state": "Sumatera Utara",
    "country": "INDONESIA",
    "color": "#41ab5d",
    "count": 1
  },
  {
    "lat": 0.1302785,
    "lon": 102.0736516,
    "failed": false,
    "year": "2023",
    "tablet": "Agapao",
    "city": "Sorek",
    "state": "Riau",
    "country": "INDONESIA",
    "color": "#41ab5d",
    "count": 1
  },
  {
    "lat": 2.1239421,
    "lon": 99.9894967,
    "failed": false,
    "year": "2024",
    "tablet": "Agapao",
    "city": "Pangkatan",
    "state": "Sumatera Utara",
    "country": "INDONESIA",
    "color": "#41ab5d",
    "count": 1
  },
  {
    "lat": -2.4833826,
    "lon": 117.8902853,
    "failed": true,
    "year": "2024",
    "tablet": "Agapao",
    "city": "Kecamatan Parmaksian",
    "state": "North Sumatra",
    "country": "INDONESIA",
    "color": "#FF0000",
    "count": 1
  },
  {
    "lat": 0.5397491,
    "lon": 101.5205329,
    "failed": false,
    "year": "2024",
    "tablet": "Agapao",
    "city": "Riau",
    "state": "Riau",
    "country": "INDONESIA",
    "color": "#41ab5d",
    "count": 1
  },
  {
    "lat": 3.5894617,
    "lon": 98.6741623,
    "failed": false,
    "year": "2023",
    "tablet": "Agapao",
    "city": "Medan",
    "state": "Sumatera Utara",
    "country": "INDONESIA",
    "color": "#41ab5d",
    "count": 1
  },
  {
    "lat": 1.5219099,
    "lon": 109.413809,
    "failed": false,
    "year": "2024",
    "tablet": "Agapao",
    "city": "Sambas",
    "state": "Kalimantan Barat",
    "country": "INDONESIA",
    "color": "#41ab5d",
    "count": 1
  },
  {
    "lat": 1.367076,
    "lon": 99.2725472,
    "failed": false,
    "year": "2023",
    "tablet": "Agapao",
    "city": "Raya",
    "state": "Sumatera Utara",
    "country": "INDONESIA",
    "color": "#41ab5d",
    "count": 1
  },
  {
    "lat": 1.0229744,
    "lon": 101.0650568,
    "failed": false,
    "year": "2023",
    "tablet": "Agapao",
    "city": "Kandis",
    "state": "Riau",
    "country": "INDONESIA",
    "color": "#41ab5d",
    "count": 1
  },
  {
    "lat": -6.1761924,
    "lon": 106.6382161,
    "failed": false,
    "year": "2023",
    "tablet": "Agapao",
    "city": "Tangerang",
    "state": "Banten",
    "country": "INDONESIA",
    "color": "#41ab5d",
    "count": 1
  },
  {
    "lat": 2.9588631,
    "lon": 99.0653646,
    "failed": false,
    "year": "2023",
    "tablet": "Agapao",
    "city": "Pematang Siantar",
    "state": "Sumatera Utara",
    "country": "INDONESIA",
    "color": "#41ab5d",
    "count": 1
  },
  {
    "lat": 1.367076,
    "lon": 99.2725472,
    "failed": false,
    "year": "2024",
    "tablet": "Agapao",
    "city": "Raya",
    "state": "Sumatera Utara",
    "country": "INDONESIA",
    "color": "#41ab5d",
    "count": 1
  },
  {
    "lat": 3.5894617,
    "lon": 98.6741623,
    "failed": false,
    "year": "2023",
    "tablet": "Agapao",
    "city": "Medan",
    "state": "Sumatera Utara",
    "country": "INDONESIA",
    "color": "#41ab5d",
    "count": 1
  },
  {
    "lat": -6.2349858,
    "lon": 106.9945444,
    "failed": false,
    "year": "2023",
    "tablet": "Agapao",
    "city": "Kota Bekasi",
    "state": "Jawa Barat",
    "country": "INDONESIA",
    "color": "#41ab5d",
    "count": 1
  },
  {
    "lat": 0.1302785,
    "lon": 102.0736516,
    "failed": false,
    "year": "2023",
    "tablet": "Agapao",
    "city": "Sorek",
    "state": "Riau",
    "country": "INDONESIA",
    "color": "#41ab5d",
    "count": 1
  },
  {
    "lat": 2.4447878,
    "lon": 99.1560688,
    "failed": false,
    "year": "2023",
    "tablet": "Agapao",
    "city": "Porsea",
    "state": "Sumatera Utara",
    "country": "INDONESIA",
    "color": "#41ab5d",
    "count": 1
  },
  {
    "lat": -2.4833826,
    "lon": 117.8902853,
    "failed": true,
    "year": "2024",
    "tablet": "Agapao",
    "city": "Kecamatan Parmaksian",
    "state": "North Sumatra",
    "country": "INDONESIA",
    "color": "#FF0000",
    "count": 1
  },
  {
    "lat": 3.3423355,
    "lon": 97.9292046,
    "failed": false,
    "year": "2024",
    "tablet": "Agapao",
    "city": "Lawe Sigala-gala",
    "state": "Aceh",
    "country": "INDONESIA",
    "color": "#41ab5d",
    "count": 1
  },
  {
    "lat": 2.212975,
    "lon": 98.9762353,
    "failed": false,
    "year": "2024",
    "tablet": "Agapao",
    "city": "Siborong-Borong",
    "state": "Sumatera Utara",
    "country": "INDONESIA",
    "color": "#41ab5d",
    "count": 1
  },
  {
    "lat": 3.28347,
    "lon": 98.6156331,
    "failed": false,
    "year": "2024",
    "tablet": "Agapao",
    "city": "Mardinding",
    "state": "Sumatera Utara",
    "country": "INDONESIA",
    "color": "#41ab5d",
    "count": 1
  },
  {
    "lat": 3.1547891,
    "lon": 98.3688115,
    "failed": false,
    "year": "2024",
    "tablet": "Agapao",
    "city": "Mardingding",
    "state": "Sumatera Utara",
    "country": "INDONESIA",
    "color": "#41ab5d",
    "count": 1
  },
  {
    "lat": 3.2703906,
    "lon": 98.9359416,
    "failed": false,
    "year": "2024",
    "tablet": "Agapao",
    "city": "Silau Kahean",
    "state": "North Sumatra",
    "country": "INDONESIA",
    "color": "#41ab5d",
    "count": 1
  },
  {
    "lat": 3.1168006,
    "lon": 98.1013474,
    "failed": false,
    "year": "2023",
    "tablet": "Agapao",
    "city": "Laubaleng",
    "state": "North Sumatra",
    "country": "INDONESIA",
    "color": "#41ab5d",
    "count": 1
  },
  {
    "lat": -0.3731888,
    "lon": 102.2797084,
    "failed": false,
    "year": "2023",
    "tablet": "Agapao",
    "city": "Air Molek",
    "state": "Riau",
    "country": "INDONESIA",
    "color": "#41ab5d",
    "count": 1
  },
  {
    "lat": 3.1547891,
    "lon": 98.3688115,
    "failed": false,
    "year": "2024",
    "tablet": "Agapao",
    "city": "Mardingding",
    "state": "Sumatera Utara",
    "country": "INDONESIA",
    "color": "#41ab5d",
    "count": 1
  },
  {
    "lat": 3.5894617,
    "lon": 98.6741623,
    "failed": false,
    "year": "2023",
    "tablet": "Agapao",
    "city": "Medan",
    "state": "Sumatera Utara",
    "country": "INDONESIA",
    "color": "#41ab5d",
    "count": 1
  },
  {
    "lat": -2.9888243,
    "lon": 104.7568507,
    "failed": false,
    "year": "2024",
    "tablet": "Agapao",
    "city": "Palembang",
    "state": "Sumatera Selatan",
    "country": "INDONESIA",
    "color": "#41ab5d",
    "count": 1
  },
  {
    "lat": -6.8731527,
    "lon": 107.5423099,
    "failed": false,
    "year": "2023",
    "tablet": "Agapao",
    "city": "Cimahi",
    "state": "Jawa Barat",
    "country": "INDONESIA",
    "color": "#41ab5d",
    "count": 1
  },
  {
    "lat": -6.2628908,
    "lon": 106.8822289,
    "failed": false,
    "year": "2023",
    "tablet": "Agapao",
    "city": "Jakarta Timur",
    "state": "DKI Jakarta",
    "country": "INDONESIA",
    "color": "#41ab5d",
    "count": 1
  },
  {
    "lat": 2.1239421,
    "lon": 99.9894967,
    "failed": false,
    "year": "2023",
    "tablet": "Agapao",
    "city": "Pangkatan",
    "state": "Sumatera Utara",
    "country": "INDONESIA",
    "color": "#41ab5d",
    "count": 1
  },
  {
    "lat": 2.0541345,
    "lon": 100.1428891,
    "failed": false,
    "year": "2024",
    "tablet": "Agapao",
    "city": "Kampung Rakyat",
    "state": "Sumatera Utara",
    "country": "INDONESIA",
    "color": "#41ab5d",
    "count": 1
  },
  {
    "lat": -6.2349858,
    "lon": 106.9945444,
    "failed": false,
    "year": "2025",
    "tablet": "Agapao",
    "city": "Bekasi",
    "state": "Jawa Barat",
    "country": "INDONESIA",
    "color": "#41ab5d",
    "count": 1
  },
  {
    "lat": 3.5894617,
    "lon": 98.6741623,
    "failed": false,
    "year": "2023",
    "tablet": "Agapao",
    "city": "Medan",
    "state": "Sumatera Utara",
    "country": "INDONESIA",
    "color": "#41ab5d",
    "count": 1
  },
  {
    "lat": 3.5894617,
    "lon": 98.6741623,
    "failed": false,
    "year": "2023",
    "tablet": "Agapao",
    "city": "Medan",
    "state": "Sumatera Utara",
    "country": "INDONESIA",
    "color": "#41ab5d",
    "count": 1
  },
  {
    "lat": -0.3731888,
    "lon": 102.2797084,
    "failed": false,
    "year": "2023",
    "tablet": "Agapao",
    "city": "Air Molek",
    "state": "Riau",
    "country": "INDONESIA",
    "color": "#41ab5d",
    "count": 1
  },
  {
    "lat": -7.2462836,
    "lon": 112.7377674,
    "failed": false,
    "year": "2023",
    "tablet": "Agapao",
    "city": "Surabaya",
    "state": "Jawa Timur",
    "country": "INDONESIA",
    "color": "#41ab5d",
    "count": 1
  },
  {
    "lat": -2.9888243,
    "lon": 104.7568507,
    "failed": false,
    "year": "2023",
    "tablet": "Agapao",
    "city": "Palembang",
    "state": "Sumatera Selatan",
    "country": "INDONESIA",
    "color": "#41ab5d",
    "count": 1
  },
  {
    "lat": -0.3731888,
    "lon": 102.2797084,
    "failed": false,
    "year": "2025",
    "tablet": "Agapao",
    "city": "Air Molek",
    "state": "Riau",
    "country": "INDONESIA",
    "color": "#41ab5d",
    "count": 1
  },
  {
    "lat": -0.3731888,
    "lon": 102.2797084,
    "failed": false,
    "year": "2024",
    "tablet": "Agapao",
    "city": "Air Molek",
    "state": "Riau",
    "country": "INDONESIA",
    "color": "#41ab5d",
    "count": 1
  },
  {
    "lat": 3.5894617,
    "lon": 98.6741623,
    "failed": false,
    "year": "2024",
    "tablet": "Agapao",
    "city": "Medan",
    "state": "Sumatera Utara",
    "country": "INDONESIA",
    "color": "#41ab5d",
    "count": 1
  }
]